{"alt":"Chuck Jones is a vengeful god.","day":"21","img":"https://imgs.xkcd.com/comics/engineering_hubris.png","link":"","month":"9","news":"","num":319,"safe_title":"Engineering Hubris","title":"Engineering Hubris","transcript":"[[ Landscape in the background, canyon with a winding road ]]\nMaybe engineering is the pursuit of an unattainable perfection.\nMaybe it's impossible to create something bug-free.\nMaybe I'm a fool\nMaybe the tyranny of Murphy is the penalty for hubris.\nBut I just can't shake the feeling\n[[ man standing on a box labeled \"ACME\" ]]\nWith all those supplies\n_I_ could have caught that roadrunner.\n{{Alt: Chuck Jones is a vengeful god. }}","year":"2007"}
