{"alt":"Maybe there's no tenderness in her fingertips either, but at least SHE puts out.","day":"17","img":"https://imgs.xkcd.com/comics/that_lovin_feelin.png","link":"","month":"9","news":"","num":317,"safe_title":"That Lovin' Feelin'","title":"That Lovin' Feelin'","transcript":"[[Man is in the middle of the frame, talking]]\nMan: You never close your eyes anymore when I kiss your lips and there's no tenderness like before in your fingertips.\n[[Man thoughtfully places his hand on his chin]]\nMan: Maybe I should try your sister instead.\n{{title text: Maybe there's no tenderness in her fingertips either, but at least SHE puts out.}}","year":"2007"}
